keyppc/__init__.py
keyppc/keyppc.py
keyppc-0.0.1.dist-info/LICENSE
keyppc-0.0.1.dist-info/METADATA
keyppc-0.0.1.dist-info/WHEEL
keyppc-0.0.1.dist-info/top_level.txt
keyppc-0.0.1.dist-info/RECORD
