Metadata-Version: 2.1
Name: keyppc
Version: 0.0.1
Summary: A simple library to bind your mouse and keyboard.
Home-page: https://github.com/keyywind/keyppc
Author: Keywind
Author-email: kevinwater127@gmail.com
License: UNKNOWN
Project-URL: Bug Tracker, https://github.com/keyywind/keyppc/issues
Platform: UNKNOWN
Classifier: Programming Language :: Python :: 3
Classifier: License :: OSI Approved :: MIT License
Classifier: Operating System :: OS Independent
Requires-Python: >=3.7
License-File: LICENSE
Requires-Dist: markdown
Requires-Dist: keyscraper
Requires-Dist: pynput
Requires-Dist: opencv-python
Requires-Dist: keygim
